ner_anon/__init__.py
ner_anon/anonymizer.py
ner_anon/data.py
ner_anon-0.1.3.dist-info/METADATA
ner_anon-0.1.3.dist-info/WHEEL
ner_anon-0.1.3.dist-info/top_level.txt
ner_anon-0.1.3.dist-info/RECORD
