Metadata-Version: 2.1
Name: ner_anon
Version: 0.1.3
Summary: A NER-based anonymization tool that replaces named entities in text with random entities from a given context.
Author: Aimar_bp
Classifier: Programming Language :: Python :: 3
Classifier: Operating System :: OS Independent
Requires-Python: >=3.7
Requires-Dist: transformers>=4.0.0
Requires-Dist: torch
